bin/__init__.py
bin/connect_user.py
bin/create_task.py
bin/create_user.py
bin/list_task.py
exceptions/__init__.py
exceptions/task_exceptions.py
logger/__init__.py
logger/log_config.py
models/__init__.py
models/assigned_to.py
models/db.py
models/task.py
models/task_list.py
models/user.py
todolist_Telecom-1.0.34.dist-info/METADATA
todolist_Telecom-1.0.34.dist-info/WHEEL
todolist_Telecom-1.0.34.dist-info/top_level.txt
todolist_Telecom-1.0.34.dist-info/RECORD
