Metadata-Version: 2.1
Name: todolist-Telecom
Version: 1.0.34
Summary: Bibliothèque pour gérer des tâches et des listes de tâches
Home-page: https://github.com/Top-1-KBD/to_do_list.git
Author: TOP1_organisation
Author-email: elyes.rezzoug@telecom-paris.fr
License: MIT
Keywords: todolist,tasks,task management
Classifier: Development Status :: 3 - Alpha
Classifier: Intended Audience :: Developers
Classifier: License :: OSI Approved :: MIT License
Classifier: Programming Language :: Python :: 3.9
Classifier: Programming Language :: Python :: 3.10
Classifier: Programming Language :: Python :: 3.11
Requires-Python: >=3.7, <4
Requires-Dist: pytest >=7.4.2
Requires-Dist: coverage >=7.3.2
Requires-Dist: exceptiongroup ==1.1.3
Requires-Dist: pyt ==1.0.5
Requires-Dist: safety ==2.3.5
Requires-Dist: Sphinx ==7.2.6
